setup.cfg
setup.py
staffjoy/__init__.py
staffjoy/client.py
staffjoy/config.py
staffjoy/exceptions.py
staffjoy/resource.py
staffjoy.egg-info/PKG-INFO
staffjoy.egg-info/SOURCES.txt
staffjoy.egg-info/dependency_links.txt
staffjoy.egg-info/requires.txt
staffjoy.egg-info/top_level.txt
staffjoy/resources/__init__.py
staffjoy/resources/admin.py
staffjoy/resources/apikey.py
staffjoy/resources/chomp_task.py
staffjoy/resources/cron.py
staffjoy/resources/location.py
staffjoy/resources/location_shift.py
staffjoy/resources/location_time_off_request.py
staffjoy/resources/location_timeclock.py
staffjoy/resources/manager.py
staffjoy/resources/mobius_task.py
staffjoy/resources/organization.py
staffjoy/resources/organization_worker.py
staffjoy/resources/plan.py
staffjoy/resources/preference.py
staffjoy/resources/recurring_shift.py
staffjoy/resources/role.py
staffjoy/resources/schedule.py
staffjoy/resources/schedule_shift.py
staffjoy/resources/schedule_time_off_request.py
staffjoy/resources/schedule_timeclock.py
staffjoy/resources/session.py
staffjoy/resources/shift.py
staffjoy/resources/shift_eligible_workers.py
staffjoy/resources/shift_query.py
staffjoy/resources/time_off_request.py
staffjoy/resources/timeclock.py
staffjoy/resources/user.py
staffjoy/resources/worker.py
test/__init__.py
test/test_functional.py