Metadata-Version: 1.1
Name: staffjoy
Version: 0.24
Summary: Staffjoy API Wrapper in Python
Home-page: https://github.com/staffjoy/client_python
Author: Philip Thomas
Author-email: philip@staffjoy.com
License: MIT
Download-URL: https://github.com/StaffJoy/client_python/archive/0.24.tar.gz
Keywords: staffjoy-api,staffjoy,staff joy
Platform: UNKNOWN
